port_cloud/__init__.py
port_cloud/__main__.py
port_cloud/forms.py
port_cloud/models.py
port_cloud/port_cloud.db
port_cloud/requirements.txt
port_cloud/routes.py
port_cloud/templates/base.html
port_cloud/templates/home.html
port_cloud/templates/includes/items_modals.html
port_cloud/templates/includes/owned_items_modals.html
port_cloud/templates/login.html
port_cloud/templates/market.html
port_cloud/templates/register.html
port_cloud/templates/terminal.html
port_cloud/templates/tmp.htm
port_cloud-0.1.1.dist-info/WHEEL
port_cloud-0.1.1.dist-info/METADATA
port_cloud-0.1.1.dist-info/RECORD
