Metadata-Version: 2.1
Name: port-cloud
Version: 0.1.1
Summary: port cloud terminal
Author: ported
Author-email: shahinmondal42bd@gmail.com
Requires-Python: >=3.10,<4.0
Classifier: Programming Language :: Python :: 3
Classifier: Programming Language :: Python :: 3.10
Requires-Dist: Flask (>=2.1.2,<3.0.0)
Requires-Dist: Flask-Bcrypt (>=1.0.1,<2.0.0)
Requires-Dist: Flask-Login (>=0.6.1,<0.7.0)
Requires-Dist: Flask-SQLAlchemy (>=2.5.1,<3.0.0)
Requires-Dist: Flask-SocketIO (>=5.2.0,<6.0.0)
Requires-Dist: Flask-WTF (>=1.0.1,<2.0.0)
Requires-Dist: email-validator (>=1.2.1,<2.0.0)
Requires-Dist: pendulum (>=2.1.2,<3.0.0)
